lightcurator/__init__.py
lightcurator/calibration.py
lightcurator/lcdb.py
lightcurator/lightcurve.py
tests/__init__.py
tests/test_lightcurve.py
lightcurator-1.0a5.dist-info/METADATA
lightcurator-1.0a5.dist-info/WHEEL
lightcurator-1.0a5.dist-info/top_level.txt
lightcurator-1.0a5.dist-info/RECORD
