Metadata-Version: 2.1
Name: lightcurator
Version: 1.0a5
Summary: Creates a lightcurve database of series of images.
Home-page: https://github.com/moemyself3/lightcurator
Author: Moises Castillo
Author-email: castillo.moises11@gmail.com
License: MIT License
Platform: UNKNOWN
Classifier: License :: OSI Approved :: MIT License
Requires-Dist: astroalign (==1.0.1)
Requires-Dist: astropy (>=3.1.2)
Requires-Dist: astroquery (>=0.3)
Requires-Dist: matplotlib (>=2.0.2)
Requires-Dist: numpy (>=1.14.2)
Requires-Dist: photutils (>=0.6)
Requires-Dist: ccdproc (>=1.2.0)
